src/__init__.py
src/cobra/__init__.py
src/cobra/connenction_types.py
src/cobra/controller.py
src/cobra/project.py
src/cobra/vcs.py
src/cobra/conf/__init__.py
src/cobra/conf/config.py
src/cobra/conf/vcs.yml
src/cobra/utils/__init__.py
src/cobra/utils/command_line.py
src/cobra/utils/constants.py
src/cobra/utils/exceptions.py
src/cobra/utils/module_functions.py
src/cobra/utils/post-commit
src/cobra/utils/utils.py
tests/__init__.py
tests/test_config.py
tests/test_project.py
tests/test_utils.py
tests/utils/__init__.py
tests/utils/utils.py
cobra_projects-0.1.9a2.dist-info/LICENSE
cobra_projects-0.1.9a2.dist-info/METADATA
cobra_projects-0.1.9a2.dist-info/WHEEL
cobra_projects-0.1.9a2.dist-info/entry_points.txt
cobra_projects-0.1.9a2.dist-info/top_level.txt
cobra_projects-0.1.9a2.dist-info/RECORD
