Metadata-Version: 2.1
Name: cobra-projects
Version: 0.1.9a2
Summary: A tool to create and maintain your python projects
Home-page: https://github.com/lvoegtlin/cobra
Author: Lars Voegtlin
Author-email: lars.voegtlin@unifr.ch
License: MIT
Platform: UNKNOWN
Requires-Python: >=3.6
Requires-Dist: keyring (==19.0.1)
Requires-Dist: pyyaml (==5.1.2)
Requires-Dist: PyInquirer (==1.0.3)
Requires-Dist: prompt-toolkit (==1.0.14)
Requires-Dist: pygithub (==1.43.6)
Requires-Dist: gitpython (==3.0.6)
Requires-Dist: tabulate (==0.8.5)
Requires-Dist: readme-renderer (>=21.0)
